binance_sdk_crypto_loan/__init__.py
binance_sdk_crypto_loan/crypto_loan.py
binance_sdk_crypto_loan/metadata.py
binance_sdk_crypto_loan/rest_api/__init__.py
binance_sdk_crypto_loan/rest_api/api/__init__.py
binance_sdk_crypto_loan/rest_api/api/flexible_rate_api.py
binance_sdk_crypto_loan/rest_api/api/stable_rate_api.py
binance_sdk_crypto_loan/rest_api/models/__init__.py
binance_sdk_crypto_loan/rest_api/models/check_collateral_repay_rate_response.py
binance_sdk_crypto_loan/rest_api/models/check_collateral_repay_rate_stable_rate_response.py
binance_sdk_crypto_loan/rest_api/models/enums.py
binance_sdk_crypto_loan/rest_api/models/flexible_loan_adjust_ltv_response.py
binance_sdk_crypto_loan/rest_api/models/flexible_loan_borrow_response.py
binance_sdk_crypto_loan/rest_api/models/flexible_loan_repay_response.py
binance_sdk_crypto_loan/rest_api/models/get_crypto_loans_income_history_response.py
binance_sdk_crypto_loan/rest_api/models/get_crypto_loans_income_history_response_inner.py
binance_sdk_crypto_loan/rest_api/models/get_flexible_loan_assets_data_response.py
binance_sdk_crypto_loan/rest_api/models/get_flexible_loan_assets_data_response_rows_inner.py
binance_sdk_crypto_loan/rest_api/models/get_flexible_loan_borrow_history_response.py
binance_sdk_crypto_loan/rest_api/models/get_flexible_loan_borrow_history_response_rows_inner.py
binance_sdk_crypto_loan/rest_api/models/get_flexible_loan_collateral_assets_data_response.py
binance_sdk_crypto_loan/rest_api/models/get_flexible_loan_collateral_assets_data_response_rows_inner.py
binance_sdk_crypto_loan/rest_api/models/get_flexible_loan_interest_rate_history_response.py
binance_sdk_crypto_loan/rest_api/models/get_flexible_loan_interest_rate_history_response_rows_inner.py
binance_sdk_crypto_loan/rest_api/models/get_flexible_loan_liquidation_history_response.py
binance_sdk_crypto_loan/rest_api/models/get_flexible_loan_liquidation_history_response_rows_inner.py
binance_sdk_crypto_loan-4.1.0.dist-info/METADATA
binance_sdk_crypto_loan-4.1.0.dist-info/WHEEL
binance_sdk_crypto_loan-4.1.0.dist-info/licenses/LICENCE
binance_sdk_crypto_loan-4.1.0.dist-info/RECORD
